fastapi_autocrud_rishabh/__init__.py
fastapi_autocrud_rishabh/exceptions.py
fastapi_autocrud_rishabh/filters.py
fastapi_autocrud_rishabh/generator.py
fastapi_autocrud_rishabh/pagination.py
fastapi_autocrud_rishabh/permissions.py
fastapi_autocrud_rishabh/router.py
fastapi_autocrud_rishabh/utils.py
fastapi_autocrud_rishabh-0.1.0.dist-info/licenses/LICENSE
fastapi_autocrud_rishabh-0.1.0.dist-info/METADATA
fastapi_autocrud_rishabh-0.1.0.dist-info/WHEEL
fastapi_autocrud_rishabh-0.1.0.dist-info/top_level.txt
fastapi_autocrud_rishabh-0.1.0.dist-info/RECORD
