Metadata-Version: 2.4
Name: fastapi-autocrud-rishabh
Version: 0.1.0
Summary: Automatically generate CRUD APIs for FastAPI with SQLAlchemy models
Author-email: Rishabh <rt0580155@gmail.com>
Maintainer-email: Rishabh <rt0580155@gmail.com>
License: MIT
Project-URL: Homepage, https://github.com/Rishabh00t/fastapi-autocrud-rishabh
Project-URL: Documentation, https://github.com/Rishabh00t/fastapi-autocrud-rishabh#readme
Project-URL: Repository, https://github.com/Rishabh00t/fastapi-autocrud-rishabh
Project-URL: Issues, https://github.com/Rishabh00t/fastapi-autocrud-rishabh/issues
Keywords: fastapi,crud,sqlalchemy,rest-api,auto-crud,api-generator,pydantic
Classifier: Development Status :: 4 - Beta
Classifier: Intended Audience :: Developers
Classifier: License :: OSI Approved :: MIT License
Classifier: Programming Language :: Python :: 3
Classifier: Programming Language :: Python :: 3.9
Classifier: Programming Language :: Python :: 3.10
Classifier: Programming Language :: Python :: 3.11
Classifier: Programming Language :: Python :: 3.12
Classifier: Framework :: FastAPI
Classifier: Topic :: Software Development :: Libraries :: Python Modules
Classifier: Topic :: Internet :: WWW/HTTP :: HTTP Servers
Requires-Python: >=3.9
License-File: LICENSE
Requires-Dist: fastapi>=0.100.0
Requires-Dist: sqlalchemy<3.0.0,>=1.4.0
Requires-Dist: pydantic<3.0.0,>=1.8.0
Provides-Extra: dev
Requires-Dist: pytest>=7.0.0; extra == "dev"
Requires-Dist: pytest-cov>=4.0.0; extra == "dev"
Requires-Dist: pytest-asyncio>=0.21.0; extra == "dev"
Requires-Dist: httpx>=0.24.0; extra == "dev"
Requires-Dist: black>=23.0.0; extra == "dev"
Requires-Dist: isort>=5.12.0; extra == "dev"
Requires-Dist: flake8>=6.0.0; extra == "dev"
Requires-Dist: mypy>=1.0.0; extra == "dev"
Dynamic: license-file
